sourceinversion/__init__.py
sourceinversion/atmospheric_measurements/__init__.py
sourceinversion/atmospheric_measurements/atmospheric_measurements.py
sourceinversion/mcmc/__init__.py
sourceinversion/mcmc/mcmc.py
sourceinversion-0.1.5.dist-info/LICENSE
sourceinversion-0.1.5.dist-info/METADATA
sourceinversion-0.1.5.dist-info/WHEEL
sourceinversion-0.1.5.dist-info/RECORD
